[{"分區代碼": "C01000", "分區次類別": "公園用地"}, {"分區代碼": "C01002", "分區次類別": "公園兼兒童遊樂場用地"}, {"分區代碼": "C01008", "分區次類別": "公園兼體育場用地"}, {"分區代碼": "A05000", "分區次類別": "文教區"}, {"分區代碼": "C21600", "分區次類別": "水溝用地"}, {"分區代碼": "B23000", "分區次類別": "加油站專用區"}, {"分區代碼": "C06000", "分區次類別": "市場用地"}, {"分區代碼": "A03210", "分區次類別": "甲種工業區"}, {"分區代碼": "A04000", "分區次類別": "行政區"}, {"分區代碼": "A01000", "分區次類別": "住宅區"}, {"分區代碼": "B18000", "分區次類別": "宗教專用區"}, {"分區代碼": "C16000", "分區次類別": "停車場用地"}, {"分區代碼": "A02000", "分區次類別": "商業區"}, {"分區代碼": "C26700", "分區次類別": "國小用地"}, {"分區代碼": "C26620", "分區次類別": "國中用地"}, {"分區代碼": "C11000", "分區次類別": "道路用地"}, {"分區代碼": "B03600", "分區次類別": "農會專用區"}, {"分區代碼": "A08000", "分區次類別": "農業區"}, {"分區代碼": "A03230", "分區次類別": "零星工業區"}, {"分區代碼": "C23610", "分區次類別": "電力事業用地"}, {"分區代碼": "B03520", "分區次類別": "電信專用區"}, {"分區代碼": "C02000", "分區次類別": "綠地"}, {"分區代碼": "C23000", "分區次類別": "機關用地"}, {"分區代碼": "B33000", "分區次類別": "殯葬專用區"}]